BUILD.bazel
MANIFEST.in
README.md
WORKSPACE
pyproject.toml
setup.py
atheris_libprotobuf_mutator/__init__.py
atheris_libprotobuf_mutator/helpers.py
atheris_libprotobuf_mutator/mutator.cc
atheris_libprotobuf_mutator/proto_fuzz_test.py
atheris_libprotobuf_mutator.egg-info/PKG-INFO
atheris_libprotobuf_mutator.egg-info/SOURCES.txt
atheris_libprotobuf_mutator.egg-info/dependency_links.txt
atheris_libprotobuf_mutator.egg-info/not-zip-safe
atheris_libprotobuf_mutator.egg-info/top_level.txt
example_fuzzers/example_proto_fuzzer.py
external/com_google_protobuf_build.patch
external/libprotobuf_mutator.BUILD