Metadata-Version: 2.1
Name: atheris-libprotobuf-mutator
Version: 0.1.2
Summary: libprotobuf-mutator bindings for Python using Atheris.
Home-page: https://github.com/google/atheris/
Author: atheris@google.com
Author-email: atheris@google.com
License: UNKNOWN
Platform: UNKNOWN
